microservice_starter/__init__.py
microservice_starter/cli.py
microservice_starter/generator.py
microservice_starter/templates/microservice_template/Dockerfile
microservice_starter/templates/microservice_template/celery.py
microservice_starter/templates/microservice_template/requirements.txt
microservice_starter/templates/microservice_template/run.py
microservice_starter/templates/microservice_template/wait_for_rabbitmq.sh
microservice_starter/templates/microservice_template/src/main.py
microservice_starter/templates/microservice_template/src/configs/cache.py
microservice_starter/templates/microservice_template/src/configs/database.py
microservice_starter/templates/microservice_template/src/configs/environment.py
microservice_starter/templates/microservice_template/src/configs/middleware.py
microservice_starter/templates/microservice_template/src/dependencies/dependencies.py
microservice_starter/templates/microservice_template/src/models/base_model.py
microservice_starter/templates/microservice_template/src/repositories/repository.py
microservice_starter/templates/microservice_template/src/routers/v1/check_router.py
microservice_starter/templates/microservice_template/src/schemas/schema.py
microservice_starter/templates/microservice_template/src/services/service.py
microservice_starter/templates/microservice_template/src/tasks/redis_utils.py
microservice_starter-0.1.3.dist-info/METADATA
microservice_starter-0.1.3.dist-info/WHEEL
microservice_starter-0.1.3.dist-info/entry_points.txt
microservice_starter-0.1.3.dist-info/top_level.txt
microservice_starter-0.1.3.dist-info/RECORD
