Metadata-Version: 2.4
Name: microservice-starter
Version: 0.1.3
Summary: CLI to scaffold a Python microservice (FastAPI + Celery + Docker) template
Author: Big Brain
License: MIT
Requires-Python: >=3.8
Requires-Dist: typer>=0.9.0
Requires-Dist: jinja2>=3.1.0
